<?xml version="1.0" encoding="UTF-8"?>
<objects serializationModel="Studio.02.02.00">
	<object class="AudioFile" id="{e769a7b0-550f-4524-99ec-efb15f006b95}">
		<property name="assetPath">
			<value>Audio Assets I like/Enemies SFX/More/electrical/EL-blow_24.wav</value>
		</property>
		<property name="frequencyInKHz">
			<value>44.0999985</value>
		</property>
		<property name="channelCount">
			<value>1</value>
		</property>
		<property name="length">
			<value>2.2824263038548751</value>
		</property>
		<relationship name="masterAssetFolder">
			<destination>{9e1740c7-ca87-41c0-96fe-d961c62059e4}</destination>
		</relationship>
	</object>
</objects>
